aade_publicity_search/__init__.py
aade_publicity_search/client.py
aade_publicity_search/utils.py
aade_publicity_search-1.0.2.dist-info/licenses/LICENCE
aade_publicity_search-1.0.2.dist-info/METADATA
aade_publicity_search-1.0.2.dist-info/WHEEL
aade_publicity_search-1.0.2.dist-info/top_level.txt
aade_publicity_search-1.0.2.dist-info/RECORD
