Metadata-Version: 2.4
Name: aade-publicity-search
Version: 1.0.2
Summary: AADE Public AFM lookup (VAT info) via SOAP
Author: Giorgos Iliopoulos
Project-URL: Homepage, https://github.com/gioiliop7/aade-publicity-search
Requires-Python: >=3.10
License-File: LICENCE
Requires-Dist: httpx
Requires-Dist: xmltodict
Dynamic: license-file
